auto_qchem-1.3.16.data/data/config.yml
auto_qchem-1.3.16.dist-info/licenses/LICENSE.md
autoqchem/__init__.py
autoqchem/db_functions.py
autoqchem/descriptor_functions.py
autoqchem/draw_utils.py
autoqchem/gaussian_input_generator.py
autoqchem/gaussian_log_extractor.py
autoqchem/helper_classes.py
autoqchem/helper_functions.py
autoqchem/molecule.py
autoqchem/openbabel_utils.py
autoqchem/rdkit_utils.py
autoqchem/sge_manager.py
autoqchem/slurm_manager.py
auto_qchem-1.3.16.dist-info/METADATA
auto_qchem-1.3.16.dist-info/WHEEL
auto_qchem-1.3.16.dist-info/top_level.txt
auto_qchem-1.3.16.dist-info/RECORD
